{
  "201001": {
    "Id": 201001,
    "UIAssets": "storyCollection_act_01",
    "CtrlName": "StoryCollectionActCtrl",
    "StartTime": "2025-10-20T10:00:00+08:00",
    "JumpTo": [
      71
    ]
  },
  "201002": {
    "Id": 201002,
    "UIAssets": "infinityTower_act_01",
    "CtrlName": "InfinityTowerActCtrl",
    "JumpTo": [
      42
    ]
  },
  "201003": {
    "Id": 201003,
    "UIAssets": "storyCollection_act_02",
    "CtrlName": "StoryCollectionActCtrl",
    "StartTime": "2025-11-11T12:00:00+08:00",
    "JumpTo": [
      71
    ]
  }
}